libshipkore/__init__.py
libshipkore/cli.py
libshipkore/libshipkore_base.py
libshipkore/book/__init__.py
libshipkore/common/__init__.py
libshipkore/common/baseservice.py
libshipkore/search/__init__.py
libshipkore/track/__init__.py
libshipkore/track/common/__init__.py
libshipkore/track/common/basetrackservice.py
libshipkore/track/models/__init__.py
libshipkore/track/models/model.py
libshipkore/track/tracker/__init__.py
libshipkore/track/tracker/abffreight.py
libshipkore/track/tracker/apc.py
libshipkore/track/tracker/asendia.py
libshipkore/track/tracker/bluedart.py
libshipkore/track/tracker/delhivery.py
libshipkore/track/tracker/dtdc.py
libshipkore/track/tracker/ecom_express.py
libshipkore/track/tracker/ekart.py
libshipkore/track/tracker/epost_global.py
libshipkore/track/tracker/fedex.py
libshipkore/track/tracker/first_flight.py
libshipkore/track/tracker/firstmile.py
libshipkore/track/tracker/gati_kwe.py
libshipkore/track/tracker/gls_us.py
libshipkore/track/tracker/i_parcel.py
libshipkore/track/tracker/lasership.py
libshipkore/track/tracker/lexship.py
libshipkore/track/tracker/ocs.py
libshipkore/track/tracker/olddominion.py
libshipkore/track/tracker/osmworldwide.py
libshipkore/track/tracker/pickrr.py
libshipkore/track/tracker/pilot_freight.py
libshipkore/track/tracker/pinteybowes.py
libshipkore/track/tracker/professional_couriers.py
libshipkore/track/tracker/rl_carriers.py
libshipkore/track/tracker/safexpress.py
libshipkore/track/tracker/saia.py
libshipkore/track/tracker/shree_tirupati_courier_services.py
libshipkore/track/tracker/shreeanjanicourier.py
libshipkore/track/tracker/shreenandancourier.py
libshipkore/track/tracker/shyplite.py
libshipkore/track/tracker/southeasternfreightlines.py
libshipkore/track/tracker/speedee.py
libshipkore/track/tracker/spoton.py
libshipkore/track/tracker/tforcefinalmile.py
libshipkore/track/tracker/trackon.py
libshipkore/track/tracker/yrc.py
libshipkore/track/tracker/zinc.py
libshipkore-0.4.2.dist-info/AUTHORS.rst
libshipkore-0.4.2.dist-info/LICENSE.rst
libshipkore-0.4.2.dist-info/METADATA
libshipkore-0.4.2.dist-info/WHEEL
libshipkore-0.4.2.dist-info/entry_points.txt
libshipkore-0.4.2.dist-info/top_level.txt
libshipkore-0.4.2.dist-info/RECORD
