Metadata-Version: 2.1
Name: libshipkore
Version: 0.4.2
Summary: Shipkore tracking library and CLI
Home-page: https://github.com/shipkore/libshipkore
Author: Innerkore
Author-email: admin@innerkore.com
License: UNKNOWN
Keywords: libshipkore
Platform: UNKNOWN
Classifier: Development Status :: 2 - Pre-Alpha
Classifier: Intended Audience :: Developers
Classifier: Natural Language :: English
Classifier: Programming Language :: Python :: 3
Classifier: Programming Language :: Python :: 3.7
Classifier: Programming Language :: Python :: 3.8
Requires-Python: >=3.7
License-File: LICENSE.rst
License-File: AUTHORS.rst
Requires-Dist: Click (>=8.0.3)
Requires-Dist: beautifulsoup4 (>=4.10.0)
Requires-Dist: python-dateutil (>=2.8.2)
Requires-Dist: requests (>=2.27.1)
Requires-Dist: pydantic (>=1.9.0)
Requires-Dist: parsel (>=1.6.0)
Requires-Dist: class-registry (>=2.1.2)
